Metadata-Version: 1.0
Name: sencrypt
Version: 0.0.7
Summary: tool to test and encrypt s3 buckets
Home-page: UNKNOWN
Author: Vipin Kasarla
Author-email: vipink70@gmail.com
License: GPLv3+
Platform: UNKNOWN
